cnpj/__init__.py
cnpj_py-0.1.0.dist-info/WHEEL
cnpj_py-0.1.0.dist-info/METADATA
cnpj_py-0.1.0.dist-info/RECORD
