Metadata-Version: 2.1
Name: cnpj-py
Version: 0.1.0
Summary: API para consulta de CNPJ (dados de empresa no Brasil).
License: MIT
Author-email: Erle Carrara <carrara.erle@gmail.com>
Requires-Python: >=3.8
